{
  "article_id": "50943",
  "category_id": "1",
  "title": "建议上街的勇士不要再拿毛泽东的画像了，拿胡锦涛的",
  "meta_description": "建议上街的勇士不要再拿毛泽东的画像了，拿胡锦涛的 - 有葱u提出扛着红旗反红旗，用毛画像来反清零反习近平。  但我觉得拿胡锦涛画像效果应该会更好，特别是能顺带科普一下二十大上胡被拖走这一幕，让更多人意识到习近平的无耻透顶。",
  "meta_keywords": "建议,上街,勇士,不要,再拿,毛泽东,画像,胡锦涛",
  "tags": [
    {
      "id": "520",
      "name": "胡锦涛"
    }
  ],
  "author": {
    "username": "[已注销]",
    "uid": null
  },
  "contents": "<div class=\"content markitup-box\">\r\n\t\t\t\t\t\t\t\t有葱u提出扛着红旗反红旗，用毛画像来反清零反习近平。<br/>\n<br/>\r\n但我觉得拿胡锦涛画像效果应该会更好，特别是能顺带科普一下二十大上胡被拖走这一幕，让更多人意识到习近平的无耻透顶。\t\t\t\t\t\t\t</div>",
  "view_count": 14772,
  "date": "2022-11-27",
  "agree_count": 29,
  "comment_count": 41
}