{
  "article_id": "62570",
  "category_id": "10",
  "title": "名言崇拜，阻止中国人进化为现代人的重要因素。",
  "meta_description": "名言崇拜，阻止中国人进化为现代人的重要因素。 - 什么叫名言崇拜？就是认为著名人物，权威机构，或者千百年流传下来有名的话是正确的。   本身这个是不成立的，因为观点或者说道理成不成立只与其本身是否可证明有关。与谁说的，与流传多久无关。 但是中国人有另外一套思考逻辑，就是名人，是成功人士。成功人士所说的是经...",
  "meta_keywords": "名言,崇拜,阻止,中国人,化为,现代,重要,因素",
  "tags": [
    {
      "id": "420",
      "name": "民主化"
    },
    {
      "id": "548",
      "name": "名言"
    }
  ],
  "author": {
    "username": "真实姓名",
    "uid": "78636"
  },
  "contents": "<div class=\"content markitup-box\">\r\n\t\t\t\t\t\t\t\t什么叫名言崇拜？就是认为著名人物，权威机构，或者千百年流传下来有名的话是正确的。<br/>\n<br/>\r\n 本身这个是不成立的，因为观点或者说道理成不成立只与其本身是否可证明有关。与谁说的，与流传多久无关。<br/>\r\n但是中国人有另外一套思考逻辑，就是名人，是成功人士。成功人士所说的是经验验证了的，所以是正确的。比如马云这个商业成功人士，他说的经营的话，就是对的。权威机构，他是权威，所以说他说的也是对的。比如人民日报的金句。几千年来没有被时间淘汰，而是流传下来了，所以这句肯定是有道理的。<br/>\n<br/>\r\n虽然以上三种名言，中国人认可的原因各不相同，但是共同点就是都与观点或者道理本身无关。这说明了啥？中国人不会从问题的根本去思考，只会从侧面去思考问题。这就是思考能力不足的表现。我曾经说中国人蠢，几千年来都是这样，名言崇拜正好也证明了这点。<br/>\n<br/>\r\n虽说佐证也有一定的证明力，但是佐证并不是可靠的证明方法。为什么？名人他是成功了。但是他一定会把自己的成功经验说出来吗？马云说的真的是真心话吗？或者说马云难道商业上的操作都是正确的吗？权威部门为什么一定是追求真理的，而不是追求稳固统治的？流传千百年的话，为什么不可以是因为这句话更容易使人上当而流传下来？<br/>\n<br/>\r\n所以说名言，不说大部分，至少很多是错的。而这种错误的名言，已经成为中国人的思想钢印。比如说，乱世当用重典。中国人就认为，杀的快，杀得多，就可以解决问题。其实这就像船漏了，拼命用桶去舀出去水一样，根本是无用的。<br/>\n<br/>\r\n比如说，卧榻之侧，岂容他人鼾睡。中国人就认为，必须干掉周边的人或者国家，不可能与他们和平共处。但是事实上呢？欧洲那些国家互相间已经和平了很久了。<br/>\n<br/>\r\n再比如宁当太平犬，不做乱世人。中国人就认为打起仗了，乱了，这种秩序崩坏的状态，一定比有秩序的暴政更苦，更容易死亡。其实事实并不是这样。根据不同情况，可能太平犬死亡率更高，比如60年，比如三年防疫，比如河北泄洪。也可能是乱世人死亡更高，这个其实是没有固定答案的。<br/>\n<br/>\r\n在中共倒台后，中国或者说诸夏，如何才能真正成为现代文明国家？前期工作，我觉得破除名言崇拜很重要。可以让中国人有正确的思考方式，可以清除很多错误的价值观。我觉得现在反贼在墙内发抖音啥的，应该在批驳名言上，多下点工夫。\t\t\t\t\t\t\t</div>",
  "view_count": 1473,
  "date": "2023-08-15",
  "agree_count": 3,
  "comment_count": 5
}