{
  "article_id": "67487",
  "category_id": "1",
  "title": "李铁的电视认罪来了",
  "meta_description": "李铁的电视认罪来了 - 包子对电视认罪有瘾，记性好的说说，这是第几个了？  [img]https://telegra.ph/file/b668f1dc7d60adfc2f3fe.jpg?width=1284&height=2668[/img]",
  "meta_keywords": "电视,认罪",
  "tags": [
    {
      "id": "1037",
      "name": "反腐"
    },
    {
      "id": "2655",
      "name": "李铁"
    }
  ],
  "author": {
    "username": "sims2011",
    "uid": "101682"
  },
  "contents": "<div class=\"content markitup-box\">\r\n\t\t\t\t\t\t\t\t包子对电视认罪有瘾，记性好的说说，这是第几个了？<br/>\n<br/>\n<a class=\"placeholder\" href=\"url/img/aHR0cHM6Ly90ZWxlZ3JhLnBoL2ZpbGUvYjY2OGYxZGM3ZDYwYWRmYzJmM2ZlLmpwZz93aWR0aD0xMjg0JmhlaWdodD0yNjY4\" rel=\"nofollow noreferrer noopener\" target=\"_blank\" title=\"https://telegra.ph/file/b668f1dc7d60adfc2f3fe.jpg?width=1284&amp;height=2668\"><img alt=\"https://telegra.ph/file/b668f1dc7d60adfc2f3fe.jpg?width=1284&amp;height=2668\" loading=\"lazy\" src=\"https://telegra.ph/file/b668f1dc7d60adfc2f3fe.jpg?width=1284&amp;height=2668\" style=\"max-width:100%\"/></a> </div>",
  "view_count": 5802,
  "date": "2024-01-05",
  "agree_count": 5,
  "comment_count": 12
}