{
  "parent_type": "question",
  "parent_id": "66241",
  "answer_count": 12,
  "answers": [
    {
      "id": "737773",
      "is_folded": false,
      "answerer": {
        "username": "我送近平上西天",
        "uid": "13149"
      },
      "contents": "<div class=\"markitup-box\">\n\t\t\t川普是那種「把別人不敢說/看不出的問題說出來，但提不出合理解決方法的人」<br/>\n正如上面葱友說了他是一個很好的監督者但不是建設者<br/>\n<br/>\n<br/>\n他說的所有問題都有理有據，但他提出的解決方法全都是一刀切簡單粗暴式的手段<br/>\n<br/>\n非法移民是不是問題？是    但他提出的方案有沒有嚴重的政治形象後果，當然有，最基本提出非法移民在美國出生的二代沒有公民身份 以及兒童和父母分離的政策，都是效果不即時但後果即時的政策<br/>\n<br/>\n歐洲盟友在北約中是不是搭了美國的便車？是。但他提出的東西會帶來其他也非常嚴重的後果 比如撤走在這些盟友領土的海外駐軍<br/>\n<br/>\n<br/>\n他就是那種少數診得出病人有菜花，但治療方法是把整根雞雞切掉的醫生\t\t</div>",
      "date": "2024-04-01",
      "agree_count": 19,
      "discussion_count": 2,
      "discussions": [
        {
          "id": "1267536",
          "replier": {
            "username": "反华分子",
            "uid": "92367"
          },
          "date": "2024-05-26",
          "content": "@我送近平上西天 如果川普不当选 美国就完了 川普是用常识治国的 爱美国的［真美国人］"
        },
        {
          "id": "1267542",
          "replier": {
            "username": "[已注销]",
            "uid": null
          },
          "date": "2024-05-26",
          "content": "有很多问题不是随便一拍脑袋就能解决的，但是至少他让别人都开始注意到这些问题了，就已经比那些连任两届但是并没有实质上让国家进步的总统要好得多"
        }
      ]
    },
    {
      "id": "737727",
      "is_folded": false,
      "answerer": {
        "username": "OrphenOfKos",
        "uid": "73371"
      },
      "contents": "<div class=\"markitup-box\">\n\t\t\t过客<br/>\n他的政策远需要2个任期 8年所可以完成的<br/>\n无论他政策是对还是错 他的政策都不会得到实施<br/>\n<br/>\n说实话他这类解构者 最佳合适的是反对党领袖而不是自己去执政\t\t</div>",
      "date": "2024-04-01",
      "agree_count": 6,
      "discussion_count": 1,
      "discussions": [
        {
          "id": "1254328",
          "replier": {
            "username": "Vinobianco",
            "uid": "93938"
          },
          "date": "2024-04-01",
          "content": "现实的解构者是白等而非川普"
        }
      ]
    },
    {
      "id": "738165",
      "is_folded": false,
      "answerer": {
        "username": "milala",
        "uid": "80511"
      },
      "contents": "<div class=\"markitup-box\">\n\t\t\t川普扯掉了左派的新衣，把这个名为民主实为独裁的政治群体的真面目给彻底展现了出来。<br/>\n另外川普是商人，他给出的方案不会是最优解，也未必是最终解，而是会根据情势发展逐渐调整，是商业方案的做法，所以盯着川普一开始说的是很肤浅的。但是洼地农逼和左派农逼理解不了这些，这些人脑子里只有绝对控制的最优方案，他们追求的就是绝对正确说一不二的大政府和大独裁者。\t\t</div>",
      "date": "2024-04-03",
      "agree_count": 5,
      "discussion_count": 0,
      "discussions": []
    },
    {
      "id": "737938",
      "is_folded": false,
      "answerer": {
        "username": "Ligur",
        "uid": "6591"
      },
      "contents": "<div class=\"markitup-box\">\n\t\t\t种种迹象表明川普实际上并没有真正的政治势力，在他第一任期末尾他自己的内阁成员都频频出来跳反他。<br/>\n另外他在自己的大本营纽约也是一塌糊涂，被地方检察官围追堵截而毫无还手之力。<br/>\n国际上的盟友更不用说了，从欧洲到日本甚至台湾都对他二次上台持保留态度。<br/>\n对我个人来说最令我不齿的一点是当初j6事件他那么多支持者转手就被他卖了，而且这几年来完全没有对那些被捕的人表达过什么，仿佛与己无关一样。所以在我看来他想当美国总话事人的话担当也是非常有问题的。<br/>\n<br/>\n综上此人甚至有些类似于台湾柯文哲一样是个网红化的表演型人物，即使能被大众选票抬进白宫他的巅峰也就到此为止了。\t\t</div>",
      "date": "2024-04-02",
      "agree_count": 5,
      "discussion_count": 5,
      "discussions": [
        {
          "id": "1254724",
          "replier": {
            "username": "rowlandheights",
            "uid": "108549"
          },
          "date": "2024-04-03",
          "content": "为J6承担责任那就是真的失去总统竞选资格了，这个责任川大大担当不起"
        },
        {
          "id": "1254733",
          "replier": {
            "username": "个个是人才",
            "uid": "96673"
          },
          "date": "2024-04-03",
          "content": "老川已经表达了很多次，自己能选上，第一件事就是赦免这些人\n你们当然看不见，那也没办法\n葱共中央也是个左窝子"
        },
        {
          "id": "1254860",
          "replier": {
            "username": "Ligur",
            "uid": "6591"
          },
          "date": "2024-04-04",
          "content": "@个个是人才:啊，真是负责呢，跟马克龙的“基辅沦陷法国就出兵”还真是异曲同工之妙。"
        },
        {
          "id": "1254938",
          "replier": {
            "username": "个个是人才",
            "uid": "96673"
          },
          "date": "2024-04-04",
          "content": "@Ligur:马克龙这两天牛逼的话可比你这挤兑的话要牛逼多了"
        },
        {
          "id": "1254940",
          "replier": {
            "username": "Ligur",
            "uid": "6591"
          },
          "date": "2024-04-04",
          "content": "@个个是人才:确实谁也比不了你川吹牛逼"
        }
      ]
    },
    {
      "id": "738112",
      "is_folded": false,
      "answerer": {
        "username": "马太监盼招安",
        "uid": "127096"
      },
      "contents": "<div class=\"markitup-box\">\n\t\t\t以前大选。克林顿 布什 奥巴马 也没有这么多 网民关注和论战，<br/>\n有分析 川普热度是 习外宣 故意操纵 <br/>\n对外制造谣言煽动美国社会动乱 <br/>\n对内 扰乱网络舆论 误导网民关注 <br/>\n从而忽略对国内 事件的 传播。<br/>\n就像 退伍兵跳出来 造谣死亡四亿<br/>\n吸引网民放弃习式防疫的舆论追责<br/>\n及时替老包背锅 诱导了舆论<br/>\n<br/>\n主导挺川的 法轮功 郭文贵团伙 都不是 什么正经玩意。<br/>\n放出的腐肉谣言吸引大量脑残网民像苍蝇一样飞来飞去。<br/>\n现在宣传已经不再用单位五毛了 效率低成本高 而且容易招致网民围攻。<br/>\n都改为水军 或者 郭式 轮式  宣传方式了。反正一群义工天天 白干活。\t\t</div>",
      "date": "2024-04-03",
      "agree_count": 2,
      "discussion_count": 0,
      "discussions": []
    },
    {
      "id": "737935",
      "is_folded": false,
      "answerer": {
        "username": "屠支大佐毛遮洞",
        "uid": "107972"
      },
      "contents": "<div class=\"markitup-box\">\n\t\t\t我们<mark>支那</mark>有一个成语，叫盖棺定论，意思是要等一个人死了以后，至少是基本上失去对社会的影响力了，才能对这个人做出最后的评价。川建国同志现在还在竞聘米国的下一任总瓢把子，谁知道他以后还会出啥妖蛾子呢。现在就说重新评价特朗普这个命题，实在是太早了吧。\t\t</div>",
      "date": "2024-04-02",
      "agree_count": 1,
      "discussion_count": 0,
      "discussions": []
    },
    {
      "id": "738665",
      "is_folded": false,
      "answerer": {
        "username": "品支",
        "uid": "119299"
      },
      "contents": "<div class=\"markitup-box\">\n\t\t\t特朗普先生当选美国总统，可以同时拯救中国和美国两个国家。\t\t</div>",
      "date": "2024-04-06",
      "agree_count": 2,
      "discussion_count": 0,
      "discussions": []
    },
    {
      "id": "738187",
      "is_folded": false,
      "answerer": {
        "username": "天下无贼",
        "uid": "19319"
      },
      "contents": "<div class=\"markitup-box\">\n\t\t\t谢邀。<br/>\n<br/>\n为什么要重新评判？川普没变过啊，保持了一贯的人设和做法，为什么要重新评判呢？<br/>\n<br/>\n反而是拜登，上台之后一些表面化的对华友好的嘴炮，曾经让多少川粉破口大骂，后来实践证明，那些只是嘴炮，实际上拜登在联合盟友一起对抗中国方面，做的远远好过川普。\t\t</div>",
      "date": "2024-04-04",
      "agree_count": 2,
      "discussion_count": 0,
      "discussions": []
    },
    {
      "id": "737932",
      "is_folded": false,
      "answerer": {
        "username": "天下旡贼",
        "uid": "36074"
      },
      "contents": "<div class=\"markitup-box\">\n\t\t\t我只想提一点，他的政策对错现在看不清，但一定会触碰其它派乃至资本的蛋糕，而且想反抗他、搞他也很简单。<br/>\n重整产业链里面涉及很多受贿贪污罪名，即使没有，其它势力也会想要他有，他即使再清白，他也只是个商人思维<br/>\n<br/>\n还有就是，你们猜川普会不会跟中共有关系，近些年川普的势力都是从网络上发展的，其中主要的就是tiktok。是否可以合理猜测川普借助tiktok引进发展自己的势力，但是掌权了还是跟中共翻脸不认人\t\t</div>",
      "date": "2024-04-02",
      "agree_count": 0,
      "discussion_count": 4,
      "discussions": [
        {
          "id": "1254722",
          "replier": {
            "username": "德州仪器",
            "uid": "93127"
          },
          "date": "2024-04-03",
          "content": "无贼哥，你又搞了一个小号吗"
        },
        {
          "id": "1254726",
          "replier": {
            "username": "rowlandheights",
            "uid": "108549"
          },
          "date": "2024-04-03",
          "content": "川大大已经推特治国过了，这下要抖音治国了？"
        },
        {
          "id": "1254752",
          "replier": {
            "username": "天下旡贼",
            "uid": "36074"
          },
          "date": "2024-04-04",
          "content": "@rowlandheights:都一样"
        },
        {
          "id": "1254753",
          "replier": {
            "username": "天下旡贼",
            "uid": "36074"
          },
          "date": "2024-04-04",
          "content": "@德州仪器: 我是无贼哥老相好，我可喜欢追着他跑了，我现在隔三差五骚扰他恶心他一下，就像他隔三差五发表支味言论一样"
        }
      ]
    },
    {
      "id": "738121",
      "is_folded": false,
      "answerer": {
        "username": "RobotRepublic",
        "uid": "101437"
      },
      "contents": "<div class=\"markitup-box\">\n\t\t\t有什么好重新评价的？他为了自己私利，撺掇民众冲击国会，公然破坏民主政体，莫非要评价他很牛逼很伟大是资本主义的掘墓人？你觉得灯塔不爽可以天天骂灯塔，但要是美国政客都像他这样搞，地球上早没灯塔了。不信你放任川普自由撺掇，看看美国人民都我不服谁就去冲击谁，实现自由打砸抢，最后他能得到一个什么烂摊子？<br/>\n<br/>\n权力可以改变一个人，川普尝过了权力的滋味，放不下手了，他都羡慕死习包子可以一辈子当king了。<br/>\n<br/>\n这么个货，还被当成奇货了。\t\t</div>",
      "date": "2024-04-03",
      "agree_count": 2,
      "discussion_count": 1,
      "discussions": [
        {
          "id": "1267541",
          "replier": {
            "username": "a222222222a",
            "uid": "127911"
          },
          "date": "2024-05-26",
          "content": "怪不得你9000个赞，说出如果不是习近平中国民主了这种话，果然不是一般的脑残啊"
        }
      ]
    },
    {
      "id": "737728",
      "is_folded": false,
      "answerer": {
        "username": "品仔",
        "uid": "124966"
      },
      "contents": "<div class=\"markitup-box\">\n\t\t\t普通网民只是社会最底层的人，而总统是最高层的人，中国到美国地理距离也是最远的，所以普通网民评价川普最多也是凭得到的几条可怜的信息来瞎子摸象而已\t\t</div>",
      "date": "2024-04-01",
      "agree_count": 1,
      "discussion_count": 0,
      "discussions": []
    },
    {
      "id": "737211",
      "is_folded": true,
      "answerer": {
        "username": "ackeach",
        "uid": "119237"
      },
      "contents": "<div class=\"markitup-box collapse\" style=\"display: block;\">\n<p class=\"aw-small-text\">**该用户被封禁，内容已自动替换**</p>公众领域施行民主原则 私人领域施行自由原则<br/>\n<br/>\nhttps://pincong.rocks/article/item_id-370465<br/>\n比如，我们中国人喜欢过年放鞭炮，那么我们城市是否允许过年期间放鞭炮，这是公众原则，用民主投票决定。<br/>\n但是是否允许在我家卧室窗户下面放，这是私人领域。任何人都不能在我家卧室窗户下面放鞭炮。因为我的窗户一定范围内属于私人领域，我有这个领域的安静权。也就是只有我自己才能决定我在这个范围内做什么。<br/>\n<br/>\n公众领域的事情不能延伸到私人领域。你民主再什么少数服从多数，你也不能投票决定大家可以在我的窗户下面放鞭炮。<br/>\n<br/>\n所以在真正的民主国家，你的问题根本不成立。因为群己区分是常识。只是我们中国人不懂而已。<br/>\n<br/>\n民主国家唯一烦恼的是群己权界。也就是哪些属于公众领域，哪些是私人领域。<br/>\n比如放鞭炮的例子，多少米以内算私人领域。多少米之外才算公众领域。这才是真正的难题。但是虽然如此，民主在协商这些领域时也比专制拍脑门合理得多。\t\t</div>",
      "date": "2024-03-29",
      "agree_count": 3,
      "discussion_count": 4,
      "discussions": [
        {
          "id": "1254213",
          "replier": {
            "username": "德州仪器",
            "uid": "93127"
          },
          "date": "2024-04-01",
          "content": "已删除"
        },
        {
          "id": "1254214",
          "replier": {
            "username": "德州仪器",
            "uid": "93127"
          },
          "date": "2024-04-01",
          "content": "祈巟"
        },
        {
          "id": "1254327",
          "replier": {
            "username": "ackeach",
            "uid": "119237"
          },
          "date": "2024-04-01",
          "content": "**该用户被封禁，内容已自动替换**\n全世界都不喜欢中国人？中国到底做了什么\nhttps://pincong.rocks/article/item_id-747136\n世界厌恶中国是因为-\n你中国即使富裕了，依然野蛮地对待自己的人民\n这在现代文明国家看来，你中国就是一个野蛮的国家，原始的文明。\n而且你又不是非洲国家那种内战，贫穷，没有钱去解决老百姓的问题\n比如 -\n中国是世界第二经济规模体，却依然存在贫穷国家才会出现的大规模人口贩卖产业和习俗。\n二次分配失灵，最穷得人看不起大病，住不起新房。高级官员看病全报销，还可以在市区好地段分福利房。\n你的劳动者天天超时工作，只有很少几乎等于没有的工伤保障。\n牺牲绿水青山，造成中国环境不可逆地恶化，食品安全，药品安全没有保障。高级官员天天吃特供食品，用免费的国外进口药。\n计划生育造成老无所养，人口雪崩。穷人死得早，高级官员个个都长寿。\n================\n这种行为，你自己换位思考一下\n你有一个邻居，家里地很大，还有一个大宅子，里面住着几十个人。\n里面有话语权的7个老爷，天天让其它人去下地干活，赚了钱自己先留大部分，剩下的一点再给点其它几十个人。这几十个人穷得看不起病，住不了好房间，只能住很偏很冷的小房间，还限制这些人生育，说我们家人太多，你们都要少生。\n然后你说，你们这样不好。你这是7个人+一群奴隶\n结果这个邻居说，你们就是嫉妒我们家大业大，你看我们家过去几十年做生意，赚了不少钱，你看我们把寨子里的道路都翻新了，这几十个穷人过去没有医保，现在也有点了，它们住的房子过去很破，我们现在给它们重新盖了一个新的偏房。\n然后你说，可是你把大部分钱都用于7个大老爷的吃喝，游玩，看病。它们在浪费钱，剩下一点才赏给你们。你们应该有民主，大家赚了钱，一起商量着分。不要大老爷分。\n这个邻居说，\n我们有自己的家庭情况，你们这是忽悠我们分家！分家就是破坏家庭团结。\n我遇到这种这种邻居，只会绕着走，少跟他们来往，绝不会喜欢它~"
        },
        {
          "id": "1254483",
          "replier": {
            "username": "德州仪器",
            "uid": "93127"
          },
          "date": "2024-04-02",
          "content": "@ackeach:等会儿去发一个你怎么评价习近平/拜登/薄熙来......？是否现在是重新评价他的时候了？"
        }
      ]
    }
  ]
}