{
  "question_id": "40048",
  "category_id": "10",
  "title": "在中国，和科学接近的很多都是暗反，这都是潜在盟友?",
  "meta_description": "在中国，和科学接近的很多都是暗反，这都是潜在盟友? - 本贴不牵扯国外，只说国内，避免又被刷屏谩骂。\n\n最典型的，回形针，表面科普，实际是暗中的反贼，中共大搞垃圾分类，不允许反对的时候，他们就出来科普分类也没用，到了垃圾场还是堆一起烧了，你只不过帮废品站节省了人力分拣出值钱的。\n垃圾分类，杜绝浪费的时候，谁敢出...",
  "meta_keywords": "中国,科学,很多,都是,暗反,潜在,盟友",
  "tags": [
    {
      "id": "231",
      "name": "中医"
    },
    {
      "id": "4305",
      "name": "徐晓冬"
    }
  ],
  "author": {
    "username": "shiyishi11",
    "uid": "63653"
  },
  "view_count": 3851,
  "contents": "<div class=\"content markitup-box\">\n\t\t\t\t\t\t\t\t本贴不牵扯国外，只说国内，避免又被刷屏谩骂。<br/>\n<br/>\n最典型的，回形针，表面科普，实际是暗中的反贼，中共大搞垃圾分类，不允许反对的时候，他们就出来科普分类也没用，到了垃圾场还是堆一起烧了，你只不过帮废品站节省了人力分拣出值钱的。<br/>\n垃圾分类，杜绝浪费的时候，谁敢出来说半个字?回形针公然阴阳怪气。<br/>\n不过他最后又想站着，又想把钱赚了，果然被粉红干老实了，你们都知道后来，不细说了。<br/>\n<br/>\n另一个贪污安保基金，打击异己的方舟子，不管反伪科学的出发点是啥。绝对铁反贼一个，以前在国内都是暗反忍着呢。<br/>\n<br/>\n另一个司马南打气功，揣着明白装糊涂，能说出反美是工作，赴美是生活，心里绝对反贼，不过双面人罢了。<br/>\n<br/>\n还有一大批反中医的，在美医学博士，都被粉红扒出来是暗反，给橄榄，或者正在干，这个内容太多，不细说了。<br/>\n<br/>\n传武领域，徐晓冬被橄榄，官司输给陈小旺四十万。中共把太极直接送进联合国非物质文化遗产，尽管是杂技类。<br/>\n<br/>\n徐晓冬粉丝什么成分多?还用我说。<br/>\n你想传统武术粉大多数绝对粉红吧，看到中共维护太极，都恨不得叫习大大万岁，拨乱反正。<br/>\n<br/>\n徐晓冬现在圆滑了许多，不像一开始，现在和传武圈修复了很多关系，也在微信直播卖起了电子烟和衣服。<br/>\n<br/>\n还有百度ufc贴吧，里边全是暗反，动不动就说某某某又辱华了，战狼出击呀，玩得不亦乐乎。不过都比较低调，毕竟百度的号不好搞。<br/>\n<br/>\n这些现代搏击，现代医学的支持者，就希望通过科学方法来看看传武和中医的真假。最简单的通过实践，比赛，废医验药，双盲实验。<br/>\n<br/>\n这些人不在乎什么祖宗的，洋人的，有用就是最好的。同理，既然传武和中医可以讨论，那社会制度有何不可?民主有啥好坏咱都来说说。<br/>\n<br/>\n这种不重视华夷之辩，只重视效果的科学思维方式，不是要了中共亲命么?<br/>\n中共的老干部病房可以全是科学，高铁可以全是科学，社会议题万万不能科学讨论，祖宗之法不可变！<br/>\n<br/>\n<br/>\n而中共就护着这些传统的，专制的产物。<br/>\n<br/>\n你看是不是在中国接近科学的都是暗反。<br/>\n<br/>\n几乎你在各种领域都能见到这种现象。他们憋的很难受，也就有天然的变革要求。\t\t\t\t\t\t\t</div>",
  "date": "2021-07-09",
  "agree_count": 4,
  "discussion_count": 0,
  "discussions": [],
  "answer_count": 7
}