{
  "question_id": "58112",
  "category_id": "6",
  "title": "印度真的有迷之自信嗎？來源何處？",
  "meta_description": "印度真的有迷之自信嗎？來源何處？ - 中國人很多迷之自信是來自共產黨一直反覆強調被列強欺凌的歷史而產生一種自卑轉自大心理  那印度也是嗎？",
  "meta_keywords": "印度,迷之,自信,來源,何處",
  "tags": [
    {
      "id": "52",
      "name": "印度"
    },
    {
      "id": "11654",
      "name": "自卑"
    }
  ],
  "author": {
    "username": "感謝習近平",
    "uid": "100154"
  },
  "view_count": 2115,
  "contents": "<div class=\"content markitup-box\">\n\t\t\t\t\t\t\t\t中國人很多迷之自信是來自共產黨一直反覆強調被列強欺凌的歷史而產生一種自卑轉自大心理<br/>\n<br/>\n那印度也是嗎？\t\t\t\t\t\t\t</div>",
  "date": "2023-05-06",
  "agree_count": 0,
  "discussion_count": 0,
  "discussions": [],
  "answer_count": 4
}