{
  "question_id": "61417",
  "category_id": "2",
  "title": "如果有人登基称帝复辟。但是治理国家的能力很强。让中国人都过上幸福生活。是否会有人反抗？",
  "meta_description": "如果有人登基称帝复辟。但是治理国家的能力很强。让中国人都过上幸福生活。是否会有人反抗？ - 税收低。全民医疗基本免费。就是回到了古代头上多了一个皇上",
  "meta_keywords": "登基,复辟,治理,国家,能力,很强,中国,人都,过上,幸福,生活,是否,反抗",
  "tags": [
    {
      "id": "503",
      "name": "中国人"
    }
  ],
  "author": {
    "username": "重庆强",
    "uid": "111825"
  },
  "view_count": 6675,
  "contents": "<div class=\"content markitup-box\">\n\t\t\t\t\t\t\t\t税收低。全民医疗基本免费。就是回到了古代头上多了一个皇上\t\t\t\t\t\t\t</div>",
  "date": "2023-09-01",
  "agree_count": -5,
  "discussion_count": 12,
  "discussions": [
    {
      "id": "1046087",
      "replier": {
        "username": "我不是机器",
        "uid": "91113"
      },
      "date": "2023-09-02",
      "content": "治理那麼糟糕，你看有人反對了嗎。"
    },
    {
      "id": "1046090",
      "replier": {
        "username": "华国锋",
        "uid": "16360"
      },
      "date": "2023-09-02",
      "content": "你还不明白专制制度上下限的问题吗？"
    },
    {
      "id": "1046123",
      "replier": {
        "username": "minigun",
        "uid": "29460"
      },
      "date": "2023-09-02",
      "content": "支性不改的明君梦"
    },
    {
      "id": "1046131",
      "replier": {
        "username": "李瑞环",
        "uid": "33525"
      },
      "date": "2023-09-02",
      "content": "竟然还有个傻逼点赞哈哈哈"
    },
    {
      "id": "1046132",
      "replier": {
        "username": "橡果滾呀滾",
        "uid": "101114"
      },
      "date": "2023-09-02",
      "content": "真有對支豬好的皇帝馬上會被支豬們蹬鼻子上臉。支豬只配張獻忠。"
    },
    {
      "id": "1046134",
      "replier": {
        "username": "衡匡偷光",
        "uid": "111241"
      },
      "date": "2023-09-02",
      "content": "@橡果滾呀滾: 的确，只能怪明君很少双修的"
    },
    {
      "id": "1046137",
      "replier": {
        "username": "衡匡偷光",
        "uid": "111241"
      },
      "date": "2023-09-02",
      "content": "@我不是机器:注意条件，人家说的是已经做成并证实的明君"
    },
    {
      "id": "1046146",
      "replier": {
        "username": "sikopinco",
        "uid": "93145"
      },
      "date": "2023-09-02",
      "content": "如果还是指望明君，那就永远没有希望"
    },
    {
      "id": "1046149",
      "replier": {
        "username": "衡匡偷光",
        "uid": "111241"
      },
      "date": "2023-09-02",
      "content": "不指望明君就更没有希望，手里没枪的，谁听你的，民主不是请客吃饭"
    },
    {
      "id": "1046239",
      "replier": {
        "username": "欽定匪軍經商",
        "uid": "102983"
      },
      "date": "2023-09-04",
      "content": "媽的，人民幣上還有殺中國人最多的毛主席呢，這種共匪明君你每天都被逼著用，你對全能獨裁者還有什麼更完美的幻想空間？"
    },
    {
      "id": "1046258",
      "replier": {
        "username": "願榮光重歸香港",
        "uid": "73805"
      },
      "date": "2023-09-04",
      "content": "笑死，點讚那些是支瘋了吧？"
    },
    {
      "id": "1046306",
      "replier": {
        "username": "隔岸觀火",
        "uid": "102219"
      },
      "date": "2023-09-05",
      "content": "那這個國家，是你們的還是皇帝的？"
    }
  ],
  "answer_count": 36
}