{
  "question_id": "61797",
  "category_id": "1",
  "title": "单论经济发展，中国比印度领先多少？",
  "meta_description": "单论经济发展，中国比印度领先多少？ - 世界银行数据  按购买力平价 (PPP)计算的人均 GDP（现价国际元）: 2022年中国21475.6，2022年印度8379.1  按购买力平价 (PPP) 衡量的居民最终消费支出（现价国际美元）： 2021年中国10.75万亿，2021年印度6.74...",
  "meta_keywords": "单论,经济发展,中国,印度,领先",
  "tags": [
    {
      "id": "52",
      "name": "印度"
    },
    {
      "id": "148",
      "name": "经济趋势"
    },
    {
      "id": "3865",
      "name": "经济状况"
    },
    {
      "id": "3923",
      "name": "发展中国家"
    }
  ],
  "author": {
    "username": "b28",
    "uid": "92230"
  },
  "view_count": 4505,
  "contents": "<div class=\"content markitup-box\">\n\t\t\t\t\t\t\t\t世界银行数据<br/>\n<br/>\n按购买力平价 (PPP)计算的人均 GDP（现价国际元）:<br/>\n2022年中国21475.6，2022年印度8379.1<br/>\n<br/>\n按购买力平价 (PPP) 衡量的居民最终消费支出（现价国际美元）：<br/>\n2021年中国10.75万亿，2021年印度6.74万亿<br/>\n<br/>\n购买力平价转换因子是在国内市场购买与在美国使用一美元购买同样数量的货物和服务所需要的一个国家的货币单位的数量。这个转换因子是适用于GDP的。\t\t\t\t\t\t\t</div>",
  "date": "2023-09-16",
  "agree_count": 2,
  "discussion_count": 11,
  "discussions": [
    {
      "id": "1047063",
      "replier": {
        "username": "心情不好",
        "uid": "82447"
      },
      "date": "2023-09-16",
      "content": "没有看到任何数字。"
    },
    {
      "id": "1047066",
      "replier": {
        "username": "天下无贼",
        "uid": "19319"
      },
      "date": "2023-09-16",
      "content": "因为中国最近几十年进步太快了，还是直接看数字吧，另外不能只挑差距小的数字"
    },
    {
      "id": "1047072",
      "replier": {
        "username": "fb_china_today",
        "uid": "8633"
      },
      "date": "2023-09-16",
      "content": "@天下无贼: 少了30%其实就没那么快了"
    },
    {
      "id": "1047073",
      "replier": {
        "username": "天下无贼",
        "uid": "19319"
      },
      "date": "2023-09-16",
      "content": "@fb_china_today: 牛粪和股指都算GDP的印度，可能虚报更高"
    },
    {
      "id": "1047074",
      "replier": {
        "username": "fb_china_today",
        "uid": "8633"
      },
      "date": "2023-09-16",
      "content": "@天下无贼: 印度还很低 但是潜力巨大 去看看人家孟买的建筑工地"
    },
    {
      "id": "1047077",
      "replier": {
        "username": "天下无贼",
        "uid": "19319"
      },
      "date": "2023-09-16",
      "content": "@fb_china_today: 这和我们聊的没啥关系吧。潜力怎么吹都行，还是看干货数据好。"
    },
    {
      "id": "1047080",
      "replier": {
        "username": "fb_china_today",
        "uid": "8633"
      },
      "date": "2023-09-16",
      "content": "@天下无贼: 心理战么, 其实都有关系"
    },
    {
      "id": "1047081",
      "replier": {
        "username": "b28",
        "uid": "92230"
      },
      "date": "2023-09-16",
      "content": "@天下无贼:比较历史数据用现值确实不合理，已修改。\n但是不同国家之间物价不同，用PPP就很合理。\n况且这又不是只对印度有利，用PPP中国和美国的差距也缩小了。"
    },
    {
      "id": "1047085",
      "replier": {
        "username": "天下无贼",
        "uid": "19319"
      },
      "date": "2023-09-16",
      "content": "@b28: 是的，比较历史数据不合理，我另一个帖子和你说了，20年前的中国汽车普及度和现在完全不可同日而语。\n用PPP衡量的最终消费支出，这个参数是可以比的，也合理，这个我承认。但这是一个“对印度相对有利”的指标，这个指标中印差距较小，“生活水平”是一个综合的概念，我觉得只用一个指标来对比，不公平，但是如果你再选一些其他的指标，可能就对印度不太有利了。这才是我说的“不能只挑差距小的数字（指标）”的意思。"
    },
    {
      "id": "1047086",
      "replier": {
        "username": "fb_china_today",
        "uid": "8633"
      },
      "date": "2023-09-16",
      "content": "@天下无贼: 老同志还是犯了只看状态不看趋势的毛病"
    },
    {
      "id": "1047087",
      "replier": {
        "username": "天下无贼",
        "uid": "19319"
      },
      "date": "2023-09-16",
      "content": "@fb_china_today:至少我一视同仁。有些小朋友分国家，有的国家看趋势，有的国家看状态………………\n双标一直是我所反对的。"
    }
  ],
  "answer_count": 17
}