{
  "question_id": "63773",
  "category_id": "6",
  "title": "周恩来是不是人才？",
  "meta_description": "周恩来是不是人才？ - [img]https://telegra.ph/file/7cdf6881d447465908bc5.jpg?width=335&height=468[/img]1907年周恩来生母病逝 1908年继母陈氏又去世  两位母亲接连病故，父亲又常年在外...",
  "meta_keywords": "周恩来,是不是,人才",
  "tags": [
    {
      "id": "3484",
      "name": "现实生活"
    }
  ],
  "author": {
    "username": "反华分子",
    "uid": "92367"
  },
  "view_count": 1692,
  "contents": "<div class=\"content markitup-box\">\n<a class=\"placeholder\" href=\"url/img/aHR0cHM6Ly90ZWxlZ3JhLnBoL2ZpbGUvN2NkZjY4ODFkNDQ3NDY1OTA4YmM1LmpwZz93aWR0aD0zMzUmaGVpZ2h0PTQ2OA\" rel=\"nofollow noreferrer noopener\" target=\"_blank\" title=\"https://telegra.ph/file/7cdf6881d447465908bc5.jpg?width=335&amp;height=468\"><img alt=\"https://telegra.ph/file/7cdf6881d447465908bc5.jpg?width=335&amp;height=468\" loading=\"lazy\" src=\"https://telegra.ph/file/7cdf6881d447465908bc5.jpg?width=335&amp;height=468\" style=\"max-width:100%\"/></a>1907年周恩来生母病逝 1908年继母陈氏又去世  两位母亲接连病故，父亲又常年在外谋生，刚满10岁的周恩来操持起照顾年幼弟弟等的家事 同年3月，经张申府和刘清扬介绍，加入了共产主义小组 应该是这个时候成为共匪 他在法国有女朋友 分手后仍然以朋友相称 1925年，周恩来与蒋介石等人相继组织领导了第一、二次东征 这个时候和蒋介石的关系还没破裂 1928年11月周恩来与向忠发、顾顺章组成中共中央特别任务委员会 下设中共特别行动科 开始做特务头子 1932年10月在宁都会议罢了毛泽东的官 顾顺章叛变都可以全身而退（全靠龙潭三杰） 周恩来老婆邓颖超19岁就在书中说愿意为了革命和周恩来一起去死 像德国的马克思主义革命者那样上断头台  从这些履历看来周恩来如果不是共匪的话是不是人生赢家？他为什么23岁就成了共匪？\t\t\t\t\t\t\t</div>",
  "date": "2023-12-06",
  "agree_count": 0,
  "discussion_count": 0,
  "discussions": [],
  "answer_count": 0
}