{
  "question_id": "66604",
  "category_id": "1",
  "title": "如何看待墙内依托QQ群的毛左组织“工总司”惨遭跨省抓捕？",
  "meta_description": "如何看待墙内依托QQ群的毛左组织“工总司”惨遭跨省抓捕？ - [img]https://telegra.ph/file/d52508f51555998019ebb.jpg?width=580&height=888[/img][img]https://telegra.ph/file/eafd97d1120387...",
  "meta_keywords": "看待,墙内,依托,qq,毛左,组织,工总司,惨遭,跨省,抓捕",
  "tags": [
    {
      "id": "194",
      "name": "毛泽东"
    },
    {
      "id": "624",
      "name": "毛左"
    }
  ],
  "author": {
    "username": "紅豆",
    "uid": "125667"
  },
  "view_count": 8165,
  "contents": "<div class=\"content markitup-box\">\n<a class=\"placeholder\" href=\"url/img/aHR0cHM6Ly90ZWxlZ3JhLnBoL2ZpbGUvZDUyNTA4ZjUxNTU1OTk4MDE5ZWJiLmpwZz93aWR0aD01ODAmaGVpZ2h0PTg4OA\" rel=\"nofollow noreferrer noopener\" target=\"_blank\" title=\"https://telegra.ph/file/d52508f51555998019ebb.jpg?width=580&amp;height=888\"><img alt=\"https://telegra.ph/file/d52508f51555998019ebb.jpg?width=580&amp;height=888\" loading=\"lazy\" src=\"https://telegra.ph/file/d52508f51555998019ebb.jpg?width=580&amp;height=888\" style=\"max-width:100%\"/></a><a class=\"placeholder\" href=\"url/img/aHR0cHM6Ly90ZWxlZ3JhLnBoL2ZpbGUvZWFmZDk3ZDExMjAzODc3ZDVhMWEyLmpwZz93aWR0aD00NjAmaGVpZ2h0PTY4OQ\" rel=\"nofollow noreferrer noopener\" target=\"_blank\" title=\"https://telegra.ph/file/eafd97d11203877d5a1a2.jpg?width=460&amp;height=689\"><img alt=\"https://telegra.ph/file/eafd97d11203877d5a1a2.jpg?width=460&amp;height=689\" loading=\"lazy\" src=\"https://telegra.ph/file/eafd97d11203877d5a1a2.jpg?width=460&amp;height=689\" style=\"max-width:100%\"/></a><a class=\"placeholder\" href=\"url/img/aHR0cHM6Ly90ZWxlZ3JhLnBoL2ZpbGUvOWIyMDFhMWI1ZTYyYzI2ODJkZjViLmpwZz93aWR0aD00NjQmaGVpZ2h0PTcyOA\" rel=\"nofollow noreferrer noopener\" target=\"_blank\" title=\"https://telegra.ph/file/9b201a1b5e62c2682df5b.jpg?width=464&amp;height=728\"><img alt=\"https://telegra.ph/file/9b201a1b5e62c2682df5b.jpg?width=464&amp;height=728\" loading=\"lazy\" src=\"https://telegra.ph/file/9b201a1b5e62c2682df5b.jpg?width=464&amp;height=728\" style=\"max-width:100%\"/></a><a class=\"placeholder\" href=\"url/img/aHR0cHM6Ly90ZWxlZ3JhLnBoL2ZpbGUvMjg4YmY0NWNjN2M5Mzc4MmY5M2FlLmpwZz93aWR0aD01NzQmaGVpZ2h0PTU1MA\" rel=\"nofollow noreferrer noopener\" target=\"_blank\" title=\"https://telegra.ph/file/288bf45cc7c93782f93ae.jpg?width=574&amp;height=550\"><img alt=\"https://telegra.ph/file/288bf45cc7c93782f93ae.jpg?width=574&amp;height=550\" loading=\"lazy\" src=\"https://telegra.ph/file/288bf45cc7c93782f93ae.jpg?width=574&amp;height=550\" style=\"max-width:100%\"/></a> </div>",
  "date": "2024-04-15",
  "agree_count": 7,
  "discussion_count": 9,
  "discussions": [
    {
      "id": "1058627",
      "replier": {
        "username": "葱花蛋汤",
        "uid": "117702"
      },
      "date": "2024-04-15",
      "content": "我特别震惊，真的会有这样的傻逼吗？这和活化石蟑螂有什么区别，感觉还活在那个“火热的年代”，怕不是有什么大病。"
    },
    {
      "id": "1058628",
      "replier": {
        "username": "Antonov一500",
        "uid": "73460"
      },
      "date": "2024-04-15",
      "content": "已删除"
    },
    {
      "id": "1058679",
      "replier": {
        "username": "陌上山花無數開",
        "uid": "101078"
      },
      "date": "2024-04-16",
      "content": "小朋友不懂事，又因为乳包罪进去了"
    },
    {
      "id": "1058722",
      "replier": {
        "username": "葱花蛋汤",
        "uid": "117702"
      },
      "date": "2024-04-17",
      "content": "@Studebaker史刁碧嘉:这种傻叉的群不要去了，这些活化石真的没有希望。"
    },
    {
      "id": "1058723",
      "replier": {
        "username": "Antonov一500",
        "uid": "73460"
      },
      "date": "2024-04-17",
      "content": "@葱花蛋汤:我其實蠻喜歡增長見識的，\n古法搞批鬥嘛，我覺得history reenactment還是蠻好玩的 (◕ㅅ◕✿)"
    },
    {
      "id": "1058724",
      "replier": {
        "username": "葱花蛋汤",
        "uid": "117702"
      },
      "date": "2024-04-17",
      "content": "@Studebaker史刁碧嘉:哈哈哈，这个形容太到位了，古法，哈哈哈，厉害厉害"
    },
    {
      "id": "1058725",
      "replier": {
        "username": "Antonov一500",
        "uid": "73460"
      },
      "date": "2024-04-17",
      "content": "@葱花蛋汤:歷史熱愛者狂喜  ๑(◕‿◕)๑"
    },
    {
      "id": "1058726",
      "replier": {
        "username": "葱花蛋汤",
        "uid": "117702"
      },
      "date": "2024-04-17",
      "content": "@Studebaker史刁碧嘉:不过确实，他们有时候会有很少见的史料或者收集的很全"
    },
    {
      "id": "1058727",
      "replier": {
        "username": "Antonov一500",
        "uid": "73460"
      },
      "date": "2024-04-17",
      "content": "@葱花蛋汤:是的，這些人在這種時候特別有趣，\n我就在這個時候一下子來扮演《活捉鄧尼金》了起來"
    }
  ],
  "answer_count": 24
}